src/__init__.py
src/main.py
tests/__init__.py
tests/test_add.py
optativa_pycicd-1.0.2.dist-info/METADATA
optativa_pycicd-1.0.2.dist-info/WHEEL
optativa_pycicd-1.0.2.dist-info/top_level.txt
optativa_pycicd-1.0.2.dist-info/RECORD
