Metadata-Version: 2.4
Name: optativa_pycicd
Version: 1.0.2
Summary: Descripción de tu proyecto
Author: Román Martínez
Author-email: rgmf@riseup.net
Requires-Dist: pytest
Requires-Dist: flake8
Dynamic: author
Dynamic: author-email
Dynamic: requires-dist
Dynamic: summary
